{
  "hash": "50dcc1b4",
  "configHash": "bf7f7534",
  "lockfileHash": "630ff435",
  "browserHash": "c0e14630",
  "optimized": {
    "react": {
      "src": "../../node_modules/react/index.js",
      "file": "react.js",
      "fileHash": "c019b263",
      "needsInterop": true
    },
    "react-dom": {
      "src": "../../node_modules/react-dom/index.js",
      "file": "react-dom.js",
      "fileHash": "f505b772",
      "needsInterop": true
    },
    "react/jsx-dev-runtime": {
      "src": "../../node_modules/react/jsx-dev-runtime.js",
      "file": "react_jsx-dev-runtime.js",
      "fileHash": "be033cca",
      "needsInterop": true
    },
    "@mui/icons-material": {
      "src": "../../node_modules/@mui/icons-material/esm/index.js",
      "file": "@mui_icons-material.js",
      "fileHash": "03ff6e8c",
      "needsInterop": false
    },
    "@mui/material": {
      "src": "../../node_modules/@mui/material/index.js",
      "file": "@mui_material.js",
      "fileHash": "c0037d59",
      "needsInterop": false
    },
    "@mui/system": {
      "src": "../../node_modules/@mui/system/esm/index.js",
      "file": "@mui_system.js",
      "fileHash": "8ffe1ee4",
      "needsInterop": false
    },
    "framer-motion": {
      "src": "../../node_modules/framer-motion/dist/es/index.mjs",
      "file": "framer-motion.js",
      "fileHash": "e53fd636",
      "needsInterop": false
    },
    "react-dom/client": {
      "src": "../../node_modules/react-dom/client.js",
      "file": "react-dom_client.js",
      "fileHash": "81ba339a",
      "needsInterop": true
    },
    "react-dom/server": {
      "src": "../../node_modules/react-dom/server.browser.js",
      "file": "react-dom_server.js",
      "fileHash": "500cf987",
      "needsInterop": true
    },
    "react-icons/ai": {
      "src": "../../node_modules/react-icons/ai/index.mjs",
      "file": "react-icons_ai.js",
      "fileHash": "b386d322",
      "needsInterop": false
    },
    "react-icons/fa": {
      "src": "../../node_modules/react-icons/fa/index.mjs",
      "file": "react-icons_fa.js",
      "fileHash": "19fcbd65",
      "needsInterop": false
    },
    "react-icons/gr": {
      "src": "../../node_modules/react-icons/gr/index.mjs",
      "file": "react-icons_gr.js",
      "fileHash": "1a64b170",
      "needsInterop": false
    },
    "react-icons/md": {
      "src": "../../node_modules/react-icons/md/index.mjs",
      "file": "react-icons_md.js",
      "fileHash": "35ea9332",
      "needsInterop": false
    },
    "react-icons/pi": {
      "src": "../../node_modules/react-icons/pi/index.mjs",
      "file": "react-icons_pi.js",
      "fileHash": "334b8331",
      "needsInterop": false
    },
    "react-icons/ti": {
      "src": "../../node_modules/react-icons/ti/index.mjs",
      "file": "react-icons_ti.js",
      "fileHash": "390a703f",
      "needsInterop": false
    },
    "react/jsx-runtime": {
      "src": "../../node_modules/react/jsx-runtime.js",
      "file": "react_jsx-runtime.js",
      "fileHash": "07b46009",
      "needsInterop": true
    },
    "styled-components": {
      "src": "../../node_modules/styled-components/dist/styled-components.browser.esm.js",
      "file": "styled-components.js",
      "fileHash": "b2fec80f",
      "needsInterop": false
    },
    "react-router-dom": {
      "src": "../../node_modules/react-router-dom/dist/index.mjs",
      "file": "react-router-dom.js",
      "fileHash": "98a57ca0",
      "needsInterop": false
    },
    "firebase/auth": {
      "src": "../../node_modules/firebase/auth/dist/esm/index.esm.js",
      "file": "firebase_auth.js",
      "fileHash": "ea683d32",
      "needsInterop": false
    },
    "firebase/app": {
      "src": "../../node_modules/firebase/app/dist/esm/index.esm.js",
      "file": "firebase_app.js",
      "fileHash": "33f2d74a",
      "needsInterop": false
    },
    "@iconify/react": {
      "src": "../../node_modules/@iconify/react/dist/iconify.js",
      "file": "@iconify_react.js",
      "fileHash": "53993a71",
      "needsInterop": false
    },
    "react-icons/io5": {
      "src": "../../node_modules/react-icons/io5/index.mjs",
      "file": "react-icons_io5.js",
      "fileHash": "38e48acc",
      "needsInterop": false
    },
    "react-icons/bi": {
      "src": "../../node_modules/react-icons/bi/index.mjs",
      "file": "react-icons_bi.js",
      "fileHash": "f80c5ac4",
      "needsInterop": false
    }
  },
  "chunks": {
    "chunk-2CLRFT34": {
      "file": "chunk-2CLRFT34.js"
    },
    "chunk-T7OI7B56": {
      "file": "chunk-T7OI7B56.js"
    },
    "chunk-J2K5GLE7": {
      "file": "chunk-J2K5GLE7.js"
    },
    "chunk-GOV7XVZ4": {
      "file": "chunk-GOV7XVZ4.js"
    },
    "chunk-XVPNPNLI": {
      "file": "chunk-XVPNPNLI.js"
    },
    "chunk-UGSEDP7T": {
      "file": "chunk-UGSEDP7T.js"
    },
    "chunk-O3WMLZWX": {
      "file": "chunk-O3WMLZWX.js"
    },
    "chunk-W24JOBID": {
      "file": "chunk-W24JOBID.js"
    },
    "chunk-EWTE5DHJ": {
      "file": "chunk-EWTE5DHJ.js"
    }
  }
}