{
  "hash": "75c08cb6",
  "configHash": "bf7f7534",
  "lockfileHash": "2b6b0018",
  "browserHash": "62e896bb",
  "optimized": {
    "react": {
      "src": "../../node_modules/react/index.js",
      "file": "react.js",
      "fileHash": "e3996d8d",
      "needsInterop": true
    },
    "react-dom": {
      "src": "../../node_modules/react-dom/index.js",
      "file": "react-dom.js",
      "fileHash": "2f77488d",
      "needsInterop": true
    },
    "react/jsx-dev-runtime": {
      "src": "../../node_modules/react/jsx-dev-runtime.js",
      "file": "react_jsx-dev-runtime.js",
      "fileHash": "3af26a8b",
      "needsInterop": true
    },
    "@mui/icons-material": {
      "src": "../../node_modules/@mui/icons-material/esm/index.js",
      "file": "@mui_icons-material.js",
      "fileHash": "5de236f7",
      "needsInterop": false
    },
    "@mui/material": {
      "src": "../../node_modules/@mui/material/index.js",
      "file": "@mui_material.js",
      "fileHash": "c4451b92",
      "needsInterop": false
    },
    "@mui/system": {
      "src": "../../node_modules/@mui/system/esm/index.js",
      "file": "@mui_system.js",
      "fileHash": "8395c0f6",
      "needsInterop": false
    },
    "framer-motion": {
      "src": "../../node_modules/framer-motion/dist/es/index.mjs",
      "file": "framer-motion.js",
      "fileHash": "ba3343a4",
      "needsInterop": false
    },
    "react-dom/client": {
      "src": "../../node_modules/react-dom/client.js",
      "file": "react-dom_client.js",
      "fileHash": "f87fc25d",
      "needsInterop": true
    },
    "react-dom/server": {
      "src": "../../node_modules/react-dom/server.browser.js",
      "file": "react-dom_server.js",
      "fileHash": "fc9debd6",
      "needsInterop": true
    },
    "react-icons/ai": {
      "src": "../../node_modules/react-icons/ai/index.mjs",
      "file": "react-icons_ai.js",
      "fileHash": "7a64ead9",
      "needsInterop": false
    },
    "react-icons/fa": {
      "src": "../../node_modules/react-icons/fa/index.mjs",
      "file": "react-icons_fa.js",
      "fileHash": "9ffe70ed",
      "needsInterop": false
    },
    "react-icons/gr": {
      "src": "../../node_modules/react-icons/gr/index.mjs",
      "file": "react-icons_gr.js",
      "fileHash": "a3a06a05",
      "needsInterop": false
    },
    "react-icons/md": {
      "src": "../../node_modules/react-icons/md/index.mjs",
      "file": "react-icons_md.js",
      "fileHash": "99bf0d0f",
      "needsInterop": false
    },
    "react-icons/pi": {
      "src": "../../node_modules/react-icons/pi/index.mjs",
      "file": "react-icons_pi.js",
      "fileHash": "822f0990",
      "needsInterop": false
    },
    "react-icons/ti": {
      "src": "../../node_modules/react-icons/ti/index.mjs",
      "file": "react-icons_ti.js",
      "fileHash": "f860883c",
      "needsInterop": false
    },
    "react/jsx-runtime": {
      "src": "../../node_modules/react/jsx-runtime.js",
      "file": "react_jsx-runtime.js",
      "fileHash": "ce379571",
      "needsInterop": true
    },
    "styled-components": {
      "src": "../../node_modules/styled-components/dist/styled-components.browser.esm.js",
      "file": "styled-components.js",
      "fileHash": "2f588f54",
      "needsInterop": false
    },
    "react-router-dom": {
      "src": "../../node_modules/react-router-dom/dist/index.mjs",
      "file": "react-router-dom.js",
      "fileHash": "518080dd",
      "needsInterop": false
    },
    "firebase/auth": {
      "src": "../../node_modules/firebase/auth/dist/esm/index.esm.js",
      "file": "firebase_auth.js",
      "fileHash": "be4f2902",
      "needsInterop": false
    },
    "firebase/app": {
      "src": "../../node_modules/firebase/app/dist/esm/index.esm.js",
      "file": "firebase_app.js",
      "fileHash": "dbe13b3a",
      "needsInterop": false
    },
    "@iconify/react": {
      "src": "../../node_modules/@iconify/react/dist/iconify.js",
      "file": "@iconify_react.js",
      "fileHash": "dc0e1805",
      "needsInterop": false
    },
    "react-icons/io5": {
      "src": "../../node_modules/react-icons/io5/index.mjs",
      "file": "react-icons_io5.js",
      "fileHash": "1838df66",
      "needsInterop": false
    },
    "react-icons/bi": {
      "src": "../../node_modules/react-icons/bi/index.mjs",
      "file": "react-icons_bi.js",
      "fileHash": "0383bc27",
      "needsInterop": false
    },
    "react-icons/tb": {
      "src": "../../node_modules/react-icons/tb/index.mjs",
      "file": "react-icons_tb.js",
      "fileHash": "bc7f7a81",
      "needsInterop": false
    },
    "react-player": {
      "src": "../../node_modules/react-player/dist/index.js",
      "file": "react-player.js",
      "fileHash": "e7e40ecd",
      "needsInterop": false
    },
    "react-icons/bs": {
      "src": "../../node_modules/react-icons/bs/index.mjs",
      "file": "react-icons_bs.js",
      "fileHash": "2a84b2d1",
      "needsInterop": false
    },
    "react-icons/fa6": {
      "src": "../../node_modules/react-icons/fa6/index.mjs",
      "file": "react-icons_fa6.js",
      "fileHash": "610c58aa",
      "needsInterop": false
    },
    "react-icons/lu": {
      "src": "../../node_modules/react-icons/lu/index.mjs",
      "file": "react-icons_lu.js",
      "fileHash": "659ef7ec",
      "needsInterop": false
    },
    "react-icons/io": {
      "src": "../../node_modules/react-icons/io/index.mjs",
      "file": "react-icons_io.js",
      "fileHash": "d6eea247",
      "needsInterop": false
    },
    "react-icons/go": {
      "src": "../../node_modules/react-icons/go/index.mjs",
      "file": "react-icons_go.js",
      "fileHash": "7fb1ac08",
      "needsInterop": false
    },
    "react-icons/cg": {
      "src": "../../node_modules/react-icons/cg/index.mjs",
      "file": "react-icons_cg.js",
      "fileHash": "6fb32f31",
      "needsInterop": false
    },
    "react-switch": {
      "src": "../../node_modules/react-switch/dist/index.dev.mjs",
      "file": "react-switch.js",
      "fileHash": "b659745c",
      "needsInterop": false
    },
    "react-icons/fi": {
      "src": "../../node_modules/react-icons/fi/index.mjs",
      "file": "react-icons_fi.js",
      "fileHash": "7601e993",
      "needsInterop": false
    },
    "react-icons/rx": {
      "src": "../../node_modules/react-icons/rx/index.mjs",
      "file": "react-icons_rx.js",
      "fileHash": "971c0309",
      "needsInterop": false
    },
    "react-icons/hi2": {
      "src": "../../node_modules/react-icons/hi2/index.mjs",
      "file": "react-icons_hi2.js",
      "fileHash": "6424828b",
      "needsInterop": false
    },
    "react-icons/ri": {
      "src": "../../node_modules/react-icons/ri/index.mjs",
      "file": "react-icons_ri.js",
      "fileHash": "551605e5",
      "needsInterop": false
    },
    "@dnd-kit/core": {
      "src": "../../node_modules/@dnd-kit/core/dist/core.esm.js",
      "file": "@dnd-kit_core.js",
      "fileHash": "620e78ca",
      "needsInterop": false
    },
    "@dnd-kit/sortable": {
      "src": "../../node_modules/@dnd-kit/sortable/dist/sortable.esm.js",
      "file": "@dnd-kit_sortable.js",
      "fileHash": "dcee8505",
      "needsInterop": false
    },
    "@dnd-kit/utilities": {
      "src": "../../node_modules/@dnd-kit/utilities/dist/utilities.esm.js",
      "file": "@dnd-kit_utilities.js",
      "fileHash": "22f2cac1",
      "needsInterop": false
    },
    "uuid": {
      "src": "../../node_modules/uuid/dist/esm-browser/index.js",
      "file": "uuid.js",
      "fileHash": "e7b15b04",
      "needsInterop": false
    },
    "react-useanimations": {
      "src": "../../node_modules/react-useanimations/index.js",
      "file": "react-useanimations.js",
      "fileHash": "bd2b7bc4",
      "needsInterop": true
    },
    "react-useanimations/lib/loading2": {
      "src": "../../node_modules/react-useanimations/lib/loading2/index.js",
      "file": "react-useanimations_lib_loading2.js",
      "fileHash": "149aa5b2",
      "needsInterop": true
    },
    "react-tooltip": {
      "src": "../../node_modules/react-tooltip/dist/react-tooltip.min.mjs",
      "file": "react-tooltip.js",
      "fileHash": "bcd2e3af",
      "needsInterop": false
    }
  },
  "chunks": {
    "react-HVY3J7SE": {
      "file": "react-HVY3J7SE.js"
    },
    "react-5CDULC6F": {
      "file": "react-5CDULC6F.js"
    },
    "Preview-BUVGW2TP": {
      "file": "Preview-BUVGW2TP.js"
    },
    "react-CTPHTRKF": {
      "file": "react-CTPHTRKF.js"
    },
    "dash.all.min-BKA3JPYD": {
      "file": "dash__all__min-BKA3JPYD.js"
    },
    "react-UWHLEQ7J": {
      "file": "react-UWHLEQ7J.js"
    },
    "dist-AQWEVF4U": {
      "file": "dist-AQWEVF4U.js"
    },
    "chunk-QZKXMT46": {
      "file": "chunk-QZKXMT46.js"
    },
    "chunk-37E64XV7": {
      "file": "chunk-37E64XV7.js"
    },
    "react-7EFFMFGE": {
      "file": "react-7EFFMFGE.js"
    },
    "chunk-ME4Q2XGQ": {
      "file": "chunk-ME4Q2XGQ.js"
    },
    "chunk-6X4HF3Q6": {
      "file": "chunk-6X4HF3Q6.js"
    },
    "chunk-ODKHH3QV": {
      "file": "chunk-ODKHH3QV.js"
    },
    "chunk-2CLRFT34": {
      "file": "chunk-2CLRFT34.js"
    },
    "chunk-3TCWFMBI": {
      "file": "chunk-3TCWFMBI.js"
    },
    "chunk-T3DLY4BJ": {
      "file": "chunk-T3DLY4BJ.js"
    },
    "chunk-5RER3LIT": {
      "file": "chunk-5RER3LIT.js"
    },
    "chunk-6PA75XNE": {
      "file": "chunk-6PA75XNE.js"
    },
    "chunk-4DSXCL6H": {
      "file": "chunk-4DSXCL6H.js"
    },
    "chunk-ZVIUJ6RF": {
      "file": "chunk-ZVIUJ6RF.js"
    },
    "chunk-W3JLIZXR": {
      "file": "chunk-W3JLIZXR.js"
    },
    "chunk-HFZ37CMS": {
      "file": "chunk-HFZ37CMS.js"
    }
  }
}